aviyal_desktop/__init__.py
aviyal_desktop/aviyal_desktop.py
aviyal_desktop/callpatch.py
aviyal_desktop/logredirector.py
aviyal_desktop/run_app.py
aviyal_desktop-0.0.3.dist-info/licenses/LICENSE
aviyal_desktop-0.0.3.dist-info/METADATA
aviyal_desktop-0.0.3.dist-info/WHEEL
aviyal_desktop-0.0.3.dist-info/top_level.txt
aviyal_desktop-0.0.3.dist-info/RECORD
