Metadata-Version: 2.4
Name: aviyal_desktop
Version: 0.0.3
Summary: an unofficial tool for running anvil app locally in desktop environment
Author-email: keralaboy <keralaboypypi@keralaboy.anonaddy.com>
License-Expression: AGPL-3.0-or-later
Project-URL: Homepage, https://github.com/its-me-abi/aviyal_desktop_library
Keywords: desktop,anvi,run,local,generate
Classifier: Development Status :: 4 - Beta
Classifier: Programming Language :: Python
Requires-Python: >=3.6
License-File: LICENSE
Requires-Dist: anvil-app-server
Requires-Dist: pyargman
Dynamic: license-file
